sweepLineRadin/ALAVLTree.py
sweepLineRadin/Classes.py
sweepLineRadin/DFunction.py
sweepLineRadin/EPAVLTree.py
sweepLineRadin/Intersection.py
sweepLineRadin/__init__.py
sweepLineRadin/sweepLineRadin.py
SweepLine115-0.0.1.dist-info/METADATA
SweepLine115-0.0.1.dist-info/WHEEL
SweepLine115-0.0.1.dist-info/top_level.txt
SweepLine115-0.0.1.dist-info/RECORD
