Metadata-Version: 2.1
Name: SweepLine115
Version: 0.0.1
Summary: a package that will find intersection points of Polygons using sweep line algorithm
Home-page: UNKNOWN
Author: Radin Sign Factory
License: UNKNOWN
Platform: UNKNOWN
Requires-Python: >=3.9
